compas_fea2/__init__.py
compas_fea2/base.py
compas_fea2/cli.py
compas_fea2/UI/__init__.py
compas_fea2/UI/viewer/__init__.py
compas_fea2/UI/viewer/shapes.py
compas_fea2/UI/viewer/viewer.py
compas_fea2/job/__init__.py
compas_fea2/job/input_file.py
compas_fea2/model/__init__.py
compas_fea2/model/bcs.py
compas_fea2/model/connectors.py
compas_fea2/model/constraints.py
compas_fea2/model/elements.py
compas_fea2/model/groups.py
compas_fea2/model/ics.py
compas_fea2/model/model.py
compas_fea2/model/nodes.py
compas_fea2/model/parts.py
compas_fea2/model/releases.py
compas_fea2/model/sections.py
compas_fea2/model/materials/__init__.py
compas_fea2/model/materials/concrete.py
compas_fea2/model/materials/material.py
compas_fea2/model/materials/steel.py
compas_fea2/model/materials/timber.py
compas_fea2/postprocess/__init__.py
compas_fea2/postprocess/checks.py
compas_fea2/postprocess/report.py
compas_fea2/postprocess/stresses.py
compas_fea2/problem/__init__.py
compas_fea2/problem/combinations.py
compas_fea2/problem/displacements.py
compas_fea2/problem/fields.py
compas_fea2/problem/loads.py
compas_fea2/problem/outputs.py
compas_fea2/problem/patterns.py
compas_fea2/problem/problem.py
compas_fea2/problem/steps_combinations.py
compas_fea2/problem/steps/__init__.py
compas_fea2/problem/steps/dynamic.py
compas_fea2/problem/steps/perturbations.py
compas_fea2/problem/steps/quasistatic.py
compas_fea2/problem/steps/static.py
compas_fea2/problem/steps/step.py
compas_fea2/results/__init__.py
compas_fea2/results/database.py
compas_fea2/results/fields.py
compas_fea2/results/histories.py
compas_fea2/results/results.py
compas_fea2/results/sql_wrapper.py
compas_fea2/units/__init__.py
compas_fea2/utilities/__init__.py
compas_fea2/utilities/_utils.py
compas_fea2/utilities/loads.py
compas_fea2-0.2.1.dist-info/AUTHORS.md
compas_fea2-0.2.1.dist-info/LICENSE
compas_fea2-0.2.1.dist-info/METADATA
compas_fea2-0.2.1.dist-info/WHEEL
compas_fea2-0.2.1.dist-info/entry_points.txt
compas_fea2-0.2.1.dist-info/top_level.txt
compas_fea2-0.2.1.dist-info/RECORD
