Metadata-Version: 2.1
Name: compas_fea2
Version: 0.2.1
Summary: This package is the 2nd generation of Finite element Analysis tools for COMPAS.
Author-email: Francesco Ranaudo <ranaudo@arch.ethz.ch>
License: MIT License
Project-URL: Homepage, https://compas-dev.github.io/compas_fea2
Project-URL: Documentation, https://compas-dev.github.io/compas_fea2
Project-URL: Repository, https://github.com/compas-dev/compas_fea2.git
Project-URL: Changelog, https://github.com/compas-dev/compas_fea2/blob/main/CHANGELOG.md
Classifier: Development Status :: 4 - Beta
Classifier: Topic :: Scientific/Engineering
Classifier: Programming Language :: Python
Classifier: Programming Language :: Python :: 3
Classifier: Programming Language :: Python :: 3.9
Classifier: Programming Language :: Python :: 3.10
Classifier: Programming Language :: Python :: 3.11
Requires-Python: >=3.9
License-File: LICENSE
License-File: AUTHORS.md
Requires-Dist: compas >=2.0
Requires-Dist: compas-gmsh
Requires-Dist: Click
Requires-Dist: matplotlib
Requires-Dist: pint
Requires-Dist: python-dotenv
Requires-Dist: sqlalchemy ==1.4
Provides-Extra: dev
Requires-Dist: attrs >=17.4 ; extra == 'dev'
Requires-Dist: black >=22.12.0 ; extra == 'dev'
Requires-Dist: bump-my-version ; extra == 'dev'
Requires-Dist: compas-invocations2 ; extra == 'dev'
Requires-Dist: compas-notebook >=0.5.0 ; extra == 'dev'
Requires-Dist: invoke >=0.14 ; extra == 'dev'
Requires-Dist: ruff ; extra == 'dev'
Requires-Dist: sphinx-compas2-theme ; extra == 'dev'
Requires-Dist: twine ; extra == 'dev'
Requires-Dist: wheel ; extra == 'dev'
